{
  "url": "http://www.baomoi.com/Nhat-Ban-ung-ho-Philippines-kien-Trung-Quoc/119/13545612.epi",
  "time": "12/04/2014 11:53",
  "title": "Nhật Bản ủng hộ Philippines kiện Trung Quốc",
  "category": "Tin tức > Thế giới",
  "description": "PNO – Ngày 11/4, Ngoại trưởng Nhật Bản Fumio Kishida và người đồng cấp Philippines Albert del Rosario đã nhất trí tăng cường hợp tác song phương trong an ninh hàng hải, một động thái được cho là nhắm đến tranh chấp lãnh thổ giữa Tokyo và Manila với Trung Quốc.",
  "content": "<tr> <td> <div> <p><span class='storyInlinePhoto'><img src='http://image.phunuonline.com.vn/news/2014/20140412/fckimage/132093532_21n.jpg' /></span></p> <p><em>Ngoại trưởng Nhật Bản Fumio Kishida (phải) và người đồng cấp Philippines Albert del Rosario - Ảnh: Xinhua</em></p> <p>Bên lề cuộc họp cấp bộ trưởng về giải trừ vũ khí hạt nhân tại Hiroshima (Nhật), Ngoại trưởng Nhật Bản Kishida đã bày tỏ sự ủng hộ của Tokyo đối với việc Philippines gần đây nộp đơn kiện Trung Quốc lên một tòa án của Liên Hợp Quốc liên quan đến tranh chấp biển đảo để phản đối việc Bắc Kinh tuyên bố chủ quyền một số bãi cát ngầm và đảo san hô trong Biển Đông thuộc chủ quyền của Philippines.</p> <p>Ông Kishida nói với báo giới rằng việc Manila “theo đuổi một giải pháp hòa bình cho các tranh chấp là căn cứ theo quy định của pháp luật”.</p> <p>Hợp tác an ninh hàng hải đã trở thành một ưu tiên đối với Nhật Bản và Philippines, khi Tokyo cũng đang đối đầu với Bắc Kinh về chủ quyền quần đảo Senkaku/Điếu Ngư trong biển Hoa Đông.</p> <p>Bên lề hội nghị Hiroshima, ông Kishida cũng có cuộc gặp riêng với Ngoại trưởng Indonesia Marty Natalegawa và hai bên nhất trí tăng cường quan hệ đối tác chiến lược giữa hai nước.</p> <p><strong>VIỆT HƯNG (Theo Kyodo)</strong></p> </div><br /></td> </tr>",
  "key": [
    "Philippines",
    "bộ trưởng ngoại giao",
    "chủ quyền",
    "Nhật Bản",
    "Tokyo",
    "Hiroshima",
    "Manila",
    "tranh chấp",
    "hàng hải",
    "nhất trí",
    "Bắc Kinh",
    "Trung Quốc",
    "Xinhua",
    "vũ khí hạt nhân",
    "Liên Hợp Quốc"
  ],
  "trends": [
    {
      "word": "Ấn Độ Dương",
      "weight": "6"
    },
    {
      "word": "Australia",
      "weight": "4"
    },
    {
      "word": "Barack Obama",
      "weight": "3"
    },
    {
      "word": "Biển Đen",
      "weight": "5"
    },
    {
      "word": "biển Đông",
      "weight": "6"
    },
    {
      "word": "Châu Âu",
      "weight": "3"
    },
    {
      "word": "Crimea",
      "weight": "1"
    },
    {
      "word": "Gazprom",
      "weight": "5"
    },
    {
      "word": "Hàn Quốc",
      "weight": "3"
    },
    {
      "word": "IMF",
      "weight": "6"
    },
    {
      "word": "Kiev",
      "weight": "1"
    },
    {
      "word": "Liên minh châu Âu",
      "weight": "2"
    },
    {
      "word": "Malaysia",
      "weight": "5"
    },
    {
      "word": "Malaysia Airlines",
      "weight": "6"
    },
    {
      "word": "máy bay chiến đấu",
      "weight": "5"
    },
    {
      "word": "Moscow",
      "weight": "3"
    },
    {
      "word": "Mỹ",
      "weight": "1"
    },
    {
      "word": "NATO",
      "weight": "2"
    },
    {
      "word": "Nga",
      "weight": "1"
    },
    {
      "word": "người biểu tình",
      "weight": "2"
    },
    {
      "word": "Nhật Bản",
      "weight": "4"
    },
    {
      "word": "Philippines",
      "weight": "4"
    },
    {
      "word": "tàu chiến",
      "weight": "4"
    },
    {
      "word": "tàu khu trục",
      "weight": "6"
    },
    {
      "word": "thủ tướng Australia",
      "weight": "4"
    },
    {
      "word": "tổng thống Nga",
      "weight": "5"
    },
    {
      "word": "Triều Tiên",
      "weight": "3"
    },
    {
      "word": "Trung Quốc",
      "weight": "2"
    },
    {
      "word": "Ukraina",
      "weight": "1"
    },
    {
      "word": "Vladimir Putin",
      "weight": "2"
    }
  ]
}
