{
  "url": "http://www.baomoi.com/Nga-bat-dau-tra-tau-chien-cho-Ukraine/119/13541632.epi",
  "time": "12/04/2014 11:54",
  "title": "Nga bắt đầu trả tàu chiến cho Ukraine",
  "category": "Tin tức > Thế giới",
  "description": "(Kienthuc.net.vn) - Nga vừa bắt đầu chuyển giao lại tàu chiến của Ukraine bị bỏ lại ở Crimea.",
  "content": "<tr> <td> <div> <div> <div> Nga vừa bắt đầu quá trình chuyển chiếc tàu chiến đầu tiên cho hải quân Ukraine, nguồn tin trong bộ chỉ huy Hạm đội Biển Đen trả lời hãng thông tấn RIA Novosti cho hay. </div> <div> “Hai tàu kéo của Hạm đội Biển Đen vừa bắt đầu kéo tàu tên lửa Priluki từ cảng Karantnnaya ở Sevatopol”, nguồn tin cho hay. </div> <div> Sau khi rời cảng Sevatopol, chiếc tàu sẽ được kéo đến vùng biển trung lập để gặp đại diện của Ukraine. </div> <div> <div> <table width='100%'> <tbody> <tr> <td><span class='storyInlinePhoto'><img src='http://cms.kienthuc.net.vn/uploaded/hoangnguyen/2014_04_11/kt_warship_ukraine_1_cryx.jpg' /></span></td> </tr> <tr> <td><em> Tàu kéo Nga đang kéo tàu tên lửa của Ukraine.<br /> </em></td> </tr> </tbody> </table> </div> Tuần trước, ông Vitaly Yarema, phó thủ tướng tạm quyền của chính phủ Ukraine từ chối đưa ra thời hạn cụ thể cho việc hoàn thành chuyển binh lính và trang thiết bị của Ukraine ra khỏi Crimea. </div> <div> “Tôi không thể khẳng định vào thời điểm hiện tại vì quá trình này phụ thuộc vào nhiều yếu tố như tốc độ và tính sẵn sàng của các phương tiện vận chuyển cũng như tình trạng của các tuyến đường sắt. Nhưng đến nay vẫn chưa có gì cản trở quá trình này”, ông Vitaly Yarema cho hay. </div> <div> Quan chức Nga cho biết nước này đã sẵn sàng để bàn giao toàn bộ vũ khí mà Ukraine bỏ lại Crimea nếu Kiev cung cấp trang thiết bị vận chuyển. </div> <div> “Bộ trưởng bộ Quốc phòng Nga đã sẵn sàng cũng như sẵn lòng để hoàn thành công việc này vào tháng 6/2014”, thứ trưởng Quốc phòng Nga Dmitry Bulgakov Dmitry Bulgakov trả lời báo chí cho hay vào ngày 9/4/2014. </div> <div> Cuộc đàm phán giữa Nga và Ukraine về chuyển giao vũ khí tập trung vào các lực lượng mặt đất và trang thiết bị. Vẫn còn khoảng 70 tàu chiến của Ukraine vẫn ở trong vùng biển của Crimea và vẫn chưa có lộ trình cụ thể để hoàn thành việc chuyển giao này. </div> <div> Cộng hòa Crimea đã tổ chức trưng cầu dân ý để quyết định ly khai Ukraine và sáp nhập vào Liên bang Nga. Có 97% người dân Crimea ủng hộ việc gia nhập Liên bang Nga. </div> <div> Sau khi sáp nhập Crimea, tổng thống Nga Putin đã ra lệnh trả lại cho phía Ukraine toàn bộ vũ khí, trang thiết bị quân sự, tàu chiến, máy bay chiến đấu của các đơn vị quân đội Ukraine đóng quân ở Crimea không muốn phục vụ trong Quân đội Nga. </div> <div> Quyết định trên được ông Putin đưa ra sau khi nhận báo cáo về công tác tiếp quản các cơ sở quân sự của quân đội Ukraine trên bán đảo Crimea từ Bộ trưởng Quốc phòng Nga Sergey Shoygu. </div> </div> <div> Ngô Trang </div> </div><br /></td> </tr> <tr> <td><span class='storyInlinePhoto'><img src='http://cms.kienthuc.net.vn/uploaded/hoangnguyen/2014_04_11/kt_warship_ukraine_1_cryx.jpg' /></span></td> </tr> <tr> <td><em> Tàu kéo Nga đang kéo tàu tên lửa của Ukraine.<br /> </em></td> </tr>",
  "key": [
    "Crimea",
    "Ukraina",
    "Nga",
    "tàu chiến",
    "trang thiết bị",
    "tàu kéo",
    "chuyển giao",
    "Biển Đen",
    "hạm đội",
    "vũ khí",
    "bộ trưởng quốc phòng",
    "RIA Novosti",
    "Kiev",
    "tổng thống Nga",
    "Vladimir Putin"
  ],
  "trends": [
    {
      "word": "Ấn Độ Dương",
      "weight": "6"
    },
    {
      "word": "Australia",
      "weight": "4"
    },
    {
      "word": "Barack Obama",
      "weight": "3"
    },
    {
      "word": "Biển Đen",
      "weight": "5"
    },
    {
      "word": "biển Đông",
      "weight": "6"
    },
    {
      "word": "Châu Âu",
      "weight": "3"
    },
    {
      "word": "Crimea",
      "weight": "1"
    },
    {
      "word": "Gazprom",
      "weight": "5"
    },
    {
      "word": "Hàn Quốc",
      "weight": "3"
    },
    {
      "word": "IMF",
      "weight": "6"
    },
    {
      "word": "Kiev",
      "weight": "1"
    },
    {
      "word": "Liên minh châu Âu",
      "weight": "2"
    },
    {
      "word": "Malaysia",
      "weight": "5"
    },
    {
      "word": "Malaysia Airlines",
      "weight": "6"
    },
    {
      "word": "máy bay chiến đấu",
      "weight": "5"
    },
    {
      "word": "Moscow",
      "weight": "3"
    },
    {
      "word": "Mỹ",
      "weight": "1"
    },
    {
      "word": "NATO",
      "weight": "2"
    },
    {
      "word": "Nga",
      "weight": "1"
    },
    {
      "word": "người biểu tình",
      "weight": "2"
    },
    {
      "word": "Nhật Bản",
      "weight": "4"
    },
    {
      "word": "Philippines",
      "weight": "4"
    },
    {
      "word": "tàu chiến",
      "weight": "4"
    },
    {
      "word": "tàu khu trục",
      "weight": "6"
    },
    {
      "word": "thủ tướng Australia",
      "weight": "4"
    },
    {
      "word": "tổng thống Nga",
      "weight": "5"
    },
    {
      "word": "Triều Tiên",
      "weight": "3"
    },
    {
      "word": "Trung Quốc",
      "weight": "2"
    },
    {
      "word": "Ukraina",
      "weight": "1"
    },
    {
      "word": "Vladimir Putin",
      "weight": "2"
    }
  ]
}
