{
  "url": "http://www.baomoi.com/My--Nhat-van-chua-thu-hep-duoc-khoang-cach-trong-TPP/119/13538991.epi",
  "time": "12/04/2014 11:55",
  "title": "Mỹ - Nhật vẫn chưa thu hẹp được khoảng cách trong TPP",
  "category": "Tin tức > Thế giới",
  "description": "VOV.VN - Hai bên vẫn chưa đạt được bất kỳ thỏa thuận nào xung quanh các vấn đề gây tranh cãi chính là công nghiệp ô tô và hàng nông sản.",
  "content": "<tr> <td> <div> <div> <div> <p> <span class='storyInlinePhoto'><img src='http://vov.vn/Uploaded/thuyanh/2014_04_11/BN-CH804_froman_G_20140410073749.jpg.ashx?width=269&height=149&crop=auto' /></span> </p> </div> </div> <p>Các nhà đàm phán của Nhật Bản và Mỹ đã không đạt được một thỏa thuận nào tại cuộc họp đầy tham vọng diễn ra trong hai ngày qua về Hiệp định đối tác xuyên Thái Bình Dương (TPP). Điều này đã làm dấy lên mối lo ngại về triển vọng đạt được một thỏa thuận trước khi Tổng thống Mỹ Barack Obama đến Nhật Bản dự hội nghị thượng đỉnh vào cuối tháng này.</p> <p>Các quan chức từ cả hai chính phủ đều hy vọng sẽ tạo ra một bước đột phá về thỏa thuận thương mại 2 chiều vào những cuộc đàm phán tới, trước thềm chuyến công tác của ông Obama vào ngày 24/4 tới. </p> <p>'Chúng tôi đã đạt được một số bước tiến trong hai ngày họp vừa qua, nhưng vẫn có sự khác biệt đáng kể trong quan điểm ở các vấn đề quan trọng'- Đại diện Thương mại Hoa Kỳ Michael Froman cho biết. </p> <p>Cả hai bên đã bắt đầu linh hoạt hơn trong việc đàm phán về các vấn đề thuế quan và bảo hộ thương mại. Bộ trưởng Kinh tế Nhật Bản Akira Amari cho biết phía Nhật đang cố gắng thu hẹp sự khác biệt giữa 2 bên trên một số vấn đề tranh cãi và không còn quá nhận định gay gắt rằng yêu cầu của phía Mỹ là bất hợp lý. Tuy nhiên, 2 bên hiện vẫn chưa thể thu hẹp khoảng cách, đặc biệt là về vấn đề ôtô và các mặt hàng nông sản. Vì vậy vẫn chưa có gì đảm bảo liệu hai bên có thể đạt được thỏa thuận nào trước cuộc họp cấp cao Mỹ - Nhật vào cuối tháng này hay không.</p> <p>Mặc dù vậy, ông Amari cho biết, cuộc gặp thượng đỉnh giữa Tổng thống Mỹ Barack Obama và Thủ tướng Nhật Bản Shinzo Abe không phải là hạn chót cho một thỏa thuận Mỹ - Nhật.</p> <p>Đến nay, tiến trình đàm phán TPP đã kéo dài 3 năm với mục tiêu thiết lập một khu vực thương mại tự do với 800 triệu dân, chiếm 30% kim ngạch thương mại toàn cầu và gần 40% sản lượng kinh tế thế giới. Các bên hy vọng một khi được ký kết, hiệp định này sẽ giúp xóa bỏ phần lớn các rào cản thương mại, đảm bảo quyền của người lao động, bảo vệ môi trường và quyền sở hữu trí tuệ./.</p> <p> CTV Thùy Anh/VOV online <br /><em>Theo WSJ</em> </p> </div> <div> <p> <span class='storyInlinePhoto'><img src='http://vov.vn/Uploaded/thuyanh/2014_04_11/BN-CH804_froman_G_20140410073749.jpg.ashx?width=269&height=149&crop=auto' /></span> </p> </div><br /></td> </tr>",
  "key": [
    "thỏa thuận",
    "Nhật Bản",
    "Barack Obama",
    "đàm phán",
    "thu hẹp",
    "thương mại",
    "nông sản",
    "họp",
    "hiệp định",
    "Mỹ",
    "tổng thống Mỹ",
    "Thái Bình Dương",
    "hội nghị thượng đỉnh",
    "đại diện thương mại",
    "thủ tướng Nhật"
  ],
  "trends": [
    {
      "word": "Ấn Độ Dương",
      "weight": "6"
    },
    {
      "word": "Australia",
      "weight": "4"
    },
    {
      "word": "Barack Obama",
      "weight": "3"
    },
    {
      "word": "Biển Đen",
      "weight": "5"
    },
    {
      "word": "biển Đông",
      "weight": "6"
    },
    {
      "word": "Châu Âu",
      "weight": "3"
    },
    {
      "word": "Crimea",
      "weight": "1"
    },
    {
      "word": "Gazprom",
      "weight": "5"
    },
    {
      "word": "Hàn Quốc",
      "weight": "3"
    },
    {
      "word": "IMF",
      "weight": "6"
    },
    {
      "word": "Kiev",
      "weight": "1"
    },
    {
      "word": "Liên minh châu Âu",
      "weight": "2"
    },
    {
      "word": "Malaysia",
      "weight": "5"
    },
    {
      "word": "Malaysia Airlines",
      "weight": "6"
    },
    {
      "word": "máy bay chiến đấu",
      "weight": "5"
    },
    {
      "word": "Moscow",
      "weight": "3"
    },
    {
      "word": "Mỹ",
      "weight": "1"
    },
    {
      "word": "NATO",
      "weight": "2"
    },
    {
      "word": "Nga",
      "weight": "1"
    },
    {
      "word": "người biểu tình",
      "weight": "2"
    },
    {
      "word": "Nhật Bản",
      "weight": "4"
    },
    {
      "word": "Philippines",
      "weight": "4"
    },
    {
      "word": "tàu chiến",
      "weight": "4"
    },
    {
      "word": "tàu khu trục",
      "weight": "6"
    },
    {
      "word": "thủ tướng Australia",
      "weight": "4"
    },
    {
      "word": "tổng thống Nga",
      "weight": "5"
    },
    {
      "word": "Triều Tiên",
      "weight": "3"
    },
    {
      "word": "Trung Quốc",
      "weight": "2"
    },
    {
      "word": "Ukraina",
      "weight": "1"
    },
    {
      "word": "Vladimir Putin",
      "weight": "2"
    }
  ]
}
