{
  "url": "http://www.baomoi.com/Nga-Ukraina-vi-pham-quyen-tu-do-cua-truyen-thong-dai-chung/119/13537110.epi",
  "time": "12/04/2014 11:56",
  "title": "Nga: Ukraina vi phạm quyền tự do của truyền thông đại chúng",
  "category": "Tin tức > Thế giới",
  "description": "Moscow sẽ yêu cầu Hội đồng Nhân quyền Liên Hợp Quốc xem xét thái độ của Ukraina với các nhà báo Nga - đại diện thường trực của Nga tại Văn phòng Liên Hợp Quốc và các tổ chức quốc tế khác tại Geneva, Aleksei Borodavkin, cho biết.",
  "content": "<tr> <td> <div> <span class='storyInlinePhoto'><img src='http://laodong.com.vn/Uploaded/phanthiphuongthuy/2014_04_11/bando_RNFG.jpg.ashx?width=660' /></span> </div> <div> <p>'Là đại diện của Nga tại Hội đồng Nhân quyền tôi có thể nói rằng, Ukraina từ chối cho các nhà báo Nga vào lãnh thổ của mình là một sự vi phạm tự do rõ ràng của truyền thông đại chúng. Chúng tôi sẽ nêu vấn đề này tại Hội đồng nhân quyền để chỉ ra rằng, những hành động như vậy là hoàn toàn không được phép'.</p> <p>'Ý kiến này của chúng tôi nhận được sự ủng hộ của nhiều tổ chức nhân quyền quốc tế và các tổ chức phi chính phủ, trong đó đã bày tỏ rõ thái độ của họ, ví dụ Ủy ban bảo vệ các nhà báo tại New York”, ông Borodavkin nói với hãng tin TASS.</p> <p>Hôm thứ tư, tổ chức phi chính phủ này kêu gọi các nhà chức trách Ukraina 'đảm bảo tất cả các nhà báo trong và ngoài nước có thể tác nghiệp một cách tự do và không bị cản trở trước các sự kiện diễn ra tại Ukraina'.</p> <p>Tổ chức an ninh và hợp tác châu Âu hôm thứ năm cho biết, hơn 20 nhà báo Nga đã bị ngăn chặn vào Ukraina để thực hiện công việc chuyên môn của mình. Trong những ngày qua, thêm 4 nhà báo thuộc các hãng thông tấn hàng đầu của Nga tiếp tục bị cấm vào Ukraina'.</p> </div> <div> <strong><i>Theo voiceofrussia</i></strong> </div><br /></td> </tr>",
  "key": [
    "Ukraina",
    "nhà báo",
    "nhân quyền",
    "Nga",
    "truyền thông đại chúng",
    "tổ chức phi chính phủ",
    "hội đồng",
    "hãng thông tấn",
    "Liên Hợp Quốc",
    "cấm vào",
    "OSCE",
    "Moscow",
    "Geneva",
    "Thành phố New York"
  ],
  "trends": [
    {
      "word": "Ấn Độ Dương",
      "weight": "6"
    },
    {
      "word": "Australia",
      "weight": "4"
    },
    {
      "word": "Barack Obama",
      "weight": "3"
    },
    {
      "word": "Biển Đen",
      "weight": "5"
    },
    {
      "word": "biển Đông",
      "weight": "6"
    },
    {
      "word": "Châu Âu",
      "weight": "3"
    },
    {
      "word": "Crimea",
      "weight": "1"
    },
    {
      "word": "Gazprom",
      "weight": "5"
    },
    {
      "word": "Hàn Quốc",
      "weight": "3"
    },
    {
      "word": "IMF",
      "weight": "6"
    },
    {
      "word": "Kiev",
      "weight": "1"
    },
    {
      "word": "Liên minh châu Âu",
      "weight": "2"
    },
    {
      "word": "Malaysia",
      "weight": "5"
    },
    {
      "word": "Malaysia Airlines",
      "weight": "6"
    },
    {
      "word": "máy bay chiến đấu",
      "weight": "5"
    },
    {
      "word": "Moscow",
      "weight": "3"
    },
    {
      "word": "Mỹ",
      "weight": "1"
    },
    {
      "word": "NATO",
      "weight": "2"
    },
    {
      "word": "Nga",
      "weight": "1"
    },
    {
      "word": "người biểu tình",
      "weight": "2"
    },
    {
      "word": "Nhật Bản",
      "weight": "4"
    },
    {
      "word": "Philippines",
      "weight": "4"
    },
    {
      "word": "tàu chiến",
      "weight": "4"
    },
    {
      "word": "tàu khu trục",
      "weight": "6"
    },
    {
      "word": "thủ tướng Australia",
      "weight": "4"
    },
    {
      "word": "tổng thống Nga",
      "weight": "5"
    },
    {
      "word": "Triều Tiên",
      "weight": "3"
    },
    {
      "word": "Trung Quốc",
      "weight": "2"
    },
    {
      "word": "Ukraina",
      "weight": "1"
    },
    {
      "word": "Vladimir Putin",
      "weight": "2"
    }
  ]
}
