{
  "url": "http://www.baomoi.com/Tim-thay-hop-den-MH370/119/13536570.epi",
  "time": "12/04/2014 11:57",
  "title": "Tìm thấy hộp đen MH370",
  "category": "Tin tức > Thế giới",
  "description": "Lực lượng tìm kiếm vừa tìm thấy hộp đen của máy bay mất tích Malaysia Airlines, theo một báo cáo chưa được xác nhận.",
  "content": "<tr> <td> <div> Trang tin News.com.au của Úc hôm nay (11-4) đưa tin lực lượng tìm kiếm vừa tìm thấy hộp đen của máy bay mất tích Malaysia Airlines, theo một báo cáo chưa được xác nhận. Thông tin chi tiết hơn sẽ được làm rõ trong cuộc họp báo ngắn sắp diễn ra của Thủ tướng Úc Tony Abbott. <div> <p> Đài phát thanh 6PR của thành phố Perth (Úc) chia sẻ trên mạng xã hội Twitter rằng thông tin nói trên do chuyên gia hàng không Geoffrey Thomas cung cấp. </p> <div type='Photo'> <div> <span class='storyInlinePhoto'><img src='http://nld.vcmedia.vn/thumb_w/540/2014/1-924556-aceec862-c124-11e3-ab5c-db8d2f3f624e-1397186996715.jpg' /></span> </div> <div> <p>Chuyên gia hàng không Geoffrey Thomas. Ảnh: AP</p> </div> </div> <p>Geoffrey Thomas là tổng biên tập của trang tin airlineratings.com , đồng thời ông cũng là biên tập chính của trang AirlineReview.com. </p> <p> Ông cho biết tàu Ocean Shield và HMS Echo đều đã rời khỏi khu vực tìm kiếm và một số nguồn tin cho biết có khả năng đã tìm thấy hộp đen. </p> <p>Vị chuyên gia hàng không uy tín này nhấn mạnh rằng thông tin vẫn chưa có xác nhận nhưng “nếu thông tin này thực sự chắc chắn” theo cách khẳng định của nguồn tin của ông thì nó đủ để Úc huy động tàu lặn không người lái Bluefin-21 lặn xuống đáy biển và chụp hình, cũng như quét thiết bị tìm kiếm ngầm.</p> <p>Trước đó, chiều 10-4, tín hiệu nghi của hộp đen mới nhất được một máy bay tuần biển AP-3C Orion của Không lực Úc bắt được trong vùng biển lân cận tàu Ocean Shield đã phát hiện 4 tín hiệu trước đó vào các ngày 6-4 và 8-4.</p> <div type='Photo'> <div> <span class='storyInlinePhoto'><img src='http://nld.vcmedia.vn/thumb_w/540/2014/1-phao-bai-1397185848541.jpg' /></span> </div> </div> <p> Tín hiệu thứ 5 này do một trong số 84 phao dò tìm tín hiệu hộp đen ở trên mặt biển thu được. Các cơ quan chức năng của Úc đã tiến hành nghiên cứu tín hiệu thứ 5 này trong đêm để xác định liệu đó có phải là tín hiệu phát ra từ hộp đen chuyến bay MH370 của hãng hàng không Malaysia bị mất tích hay không. </p> </div> <div> NLĐ(Theo News.com.au) </div> </div><br /></td> </tr>",
  "key": [
    "hộp đen",
    "tín hiệu",
    "Australia",
    "Malaysia Airlines",
    "mất tích",
    "hàng không",
    "máy bay",
    "tìm kiếm",
    "xác nhận",
    "tàu lặn",
    "Associated Press",
    "thủ tướng Australia",
    "Tony Abbott",
    "Perth",
    "mạng xã hội"
  ],
  "trends": [
    {
      "word": "Ấn Độ Dương",
      "weight": "6"
    },
    {
      "word": "Australia",
      "weight": "4"
    },
    {
      "word": "Barack Obama",
      "weight": "3"
    },
    {
      "word": "Biển Đen",
      "weight": "5"
    },
    {
      "word": "biển Đông",
      "weight": "6"
    },
    {
      "word": "Châu Âu",
      "weight": "3"
    },
    {
      "word": "Crimea",
      "weight": "1"
    },
    {
      "word": "Gazprom",
      "weight": "5"
    },
    {
      "word": "Hàn Quốc",
      "weight": "3"
    },
    {
      "word": "IMF",
      "weight": "6"
    },
    {
      "word": "Kiev",
      "weight": "1"
    },
    {
      "word": "Liên minh châu Âu",
      "weight": "2"
    },
    {
      "word": "Malaysia",
      "weight": "5"
    },
    {
      "word": "Malaysia Airlines",
      "weight": "6"
    },
    {
      "word": "máy bay chiến đấu",
      "weight": "5"
    },
    {
      "word": "Moscow",
      "weight": "3"
    },
    {
      "word": "Mỹ",
      "weight": "1"
    },
    {
      "word": "NATO",
      "weight": "2"
    },
    {
      "word": "Nga",
      "weight": "1"
    },
    {
      "word": "người biểu tình",
      "weight": "2"
    },
    {
      "word": "Nhật Bản",
      "weight": "4"
    },
    {
      "word": "Philippines",
      "weight": "4"
    },
    {
      "word": "tàu chiến",
      "weight": "4"
    },
    {
      "word": "tàu khu trục",
      "weight": "6"
    },
    {
      "word": "thủ tướng Australia",
      "weight": "4"
    },
    {
      "word": "tổng thống Nga",
      "weight": "5"
    },
    {
      "word": "Triều Tiên",
      "weight": "3"
    },
    {
      "word": "Trung Quốc",
      "weight": "2"
    },
    {
      "word": "Ukraina",
      "weight": "1"
    },
    {
      "word": "Vladimir Putin",
      "weight": "2"
    }
  ]
}
