{
  "url": "http://www.baomoi.com/My--Nhat-dam-phan-giai-quyet-be-tac-TPP/119/13529694.epi",
  "time": "12/04/2014 12:01",
  "title": "Mỹ - Nhật đàm phán giải quyết bế tắc TPP",
  "category": "Tin tức > Thế giới",
  "description": "VOV.VN - Đây là tuyên bố do đại diện thương mại Mỹ Michael Froman đưa ra hôm nay (10/4).",
  "content": "<tr> <td> <div> <div> <div> <p> <span class='storyInlinePhoto'><img src='http://vov.vn/Uploaded/thuthuy/2014_04_10/My-Trung1.jpg.ashx?width=269&height=149&crop=auto' /></span> </p> <p> Đại diện Thương mại Mỹ Michael Froman. (Nguồn: AFP) </p> </div> </div> <p>Các cuộc đàm phán thương mại giữa Nhật Bản và Mỹ diễn ra trong tuần này là rất khó khăn song các bên vẫn đang cố gắng thúc đẩy một thỏa thuận.</p> <p>Tuyên bố được đại diện thương mại Mỹ đưa ra 1 ngày sau khi các Trưởng đoàn đàm phán Nhật Bản và Mỹ bắt đầu tham gia thảo luận về những vấn đề song phương còn tồn tại liên quan đến các cuộc đàm phán thương mại tự do Đối tác xuyên Thái Bình Dương (TPP) tiến tới phá vỡ bế tắc trước chuyến thăm của Tổng thống Mỹ Barack Obama tới Tokyo vào ngày 24/4 tới. </p> <p>Đại diện thương mại Mỹ Michael Froman cho biết, trong 2 ngày đàm phán chuyên sâu, 2 bên đã đạt được một số tiến bộ, song vẫn còn những bất đồng lớn cần được giải quyết. Các cuộc đàm phán sẽ được tiếp tục trong tuần này. Mặc dù không công bố chi tiết về các cuộc đàm phán này song ông Froman cho biết, các cuộc đàm phán đề cập đến tất cả các vấn đề thương mại song phương.</p> <p>Cùng ngày, các phương tiện truyền thông Nhật Bản đưa tin, Nhật Bản đang xem xét cắt giảm thuế nhập khẩu thịt bò Mỹ xuống dưới 10% từ mức 38,5% hiện nay tại các cuộc đàm phán song phương./.</p> <p> Lệ Chi/VOV - Trung tâm Tin <br /><em>(Theo Reuters)</em> </p> </div> <div> <p> <span class='storyInlinePhoto'><img src='http://vov.vn/Uploaded/thuthuy/2014_04_10/My-Trung1.jpg.ashx?width=269&height=149&crop=auto' /></span> </p> <p> Đại diện Thương mại Mỹ Michael Froman. (Nguồn: AFP) </p> </div><br /></td> </tr>",
  "key": [
    "đại diện thương mại",
    "đàm phán",
    "Mỹ",
    "Nhật Bản",
    "song phương",
    "thương mại",
    "AFP",
    "lệ chi",
    "đàm phán song phương",
    "phương tiện truyền thông",
    "Barack Obama",
    "Thái Bình Dương",
    "tổng thống Mỹ",
    "Tokyo",
    "thuế nhập khẩu"
  ],
  "trends": [
    {
      "word": "Ấn Độ Dương",
      "weight": "6"
    },
    {
      "word": "Australia",
      "weight": "4"
    },
    {
      "word": "Barack Obama",
      "weight": "3"
    },
    {
      "word": "Biển Đen",
      "weight": "5"
    },
    {
      "word": "biển Đông",
      "weight": "6"
    },
    {
      "word": "Châu Âu",
      "weight": "3"
    },
    {
      "word": "Crimea",
      "weight": "1"
    },
    {
      "word": "Gazprom",
      "weight": "5"
    },
    {
      "word": "Hàn Quốc",
      "weight": "3"
    },
    {
      "word": "IMF",
      "weight": "6"
    },
    {
      "word": "Kiev",
      "weight": "1"
    },
    {
      "word": "Liên minh châu Âu",
      "weight": "2"
    },
    {
      "word": "Malaysia",
      "weight": "4"
    },
    {
      "word": "Malaysia Airlines",
      "weight": "5"
    },
    {
      "word": "máy bay chiến đấu",
      "weight": "6"
    },
    {
      "word": "Moscow",
      "weight": "3"
    },
    {
      "word": "Mỹ",
      "weight": "1"
    },
    {
      "word": "NATO",
      "weight": "2"
    },
    {
      "word": "Nga",
      "weight": "1"
    },
    {
      "word": "người biểu tình",
      "weight": "2"
    },
    {
      "word": "Nhật Bản",
      "weight": "5"
    },
    {
      "word": "Philippines",
      "weight": "4"
    },
    {
      "word": "tàu chiến",
      "weight": "4"
    },
    {
      "word": "thủ tướng Australia",
      "weight": "5"
    },
    {
      "word": "tổng thống Nga",
      "weight": "5"
    },
    {
      "word": "Triều Tiên",
      "weight": "3"
    },
    {
      "word": "Trung Quốc",
      "weight": "2"
    },
    {
      "word": "Ukraina",
      "weight": "1"
    },
    {
      "word": "Vladimir Putin",
      "weight": "2"
    },
    {
      "word": "Washington",
      "weight": "6"
    }
  ]
}
