{
  "url": "http://www.baomoi.com/Han-Quoc-sam-radar-Israel-de-ung-pho-UAV-Trieu-Tien/119/13521939.epi",
  "time": "12/04/2014 12:06",
  "title": "Hàn Quốc sắm radar Israel để ứng phó UAV Triều Tiên",
  "category": "Tin tức > Thế giới",
  "description": "(TNO) Hàn Quốc đang xúc tiến mua khoảng 10 radar tầm thấp của Israel nhằm nâng cao khả năng phát hiện máy bay không người lái (UAV) cỡ nhỏ và ứng phó nguy cơ CHDCND Triều Tiên đưa UAV xâm nhập Hàn Quốc, theo hãng tin Yonhap hôm nay 9.4.",
  "content": "<tr> <td> <table width='100%'> <tbody> <tr> <td> </td> </tr> <tr> <td> </td> </tr> </tbody> </table> <div> <table align='center' width='100%'> <tbody> <tr> <td> <p><span class='storyInlinePhoto'><img src='http://www.thanhnien.com.vn/Pictures201404/Minh_Nguyet/maybay06058541.jpg' /></span> <span>Một UAV rơi ở Hàn Quốc bị nghi là của Triều Tiên - Ảnh: Reuters</span></p> </td> </tr> </tbody> </table> <p>Đây là động thái mới nhất của Hàn Quốc nhằm tăng tốc việc đẩy mạnh khả năng giám sát, sau khi quân đội nước này tìm thấy <a href='http://www.thanhnien.com.vn/pages/20140406/han-quoc-phat-hien-uav-thu-3-tinh-nghi-cua-trieu-tien.aspx' target='_blank'>3 UAV</a> mà họ nghi đến từ Triều Tiên trong mấy tuần gần đây.</p> <p>Hàn Quốc hiện nay vận hành radar giám sát mặt đất và kiểm soát tên lửa TPS-840K, nhưng nó bị giới hạn trong việc phát hiện máy bay nhỏ như 3 UAV nói trên, vốn chỉ được phát hiện sau khi chúng rơi xuống đất.</p> <p>Nhằm khắc phục điểm yếu này, quân đội Hàn Quốc lập tức quyết định dành 191 triệu USD mua 10 radar tầm thấp và thiết bị giám sát khác trong năm nay để triển khai chúng đến các chốt quân sự quan trọng.</p> <p>“Chính phủ đã quyết định chuyển một phần ngân sách từ chương trình mua sắm khác để mua radar giám sát tầm thấp có khả năng phát hiện UAV nhỏ càng sớm càng tốt”, một quan chức Hàn Quốc tiết lộ với Yonhap. </p> <p>Theo đó, một đội kỹ thuật và quan chức Hàn Quốc đã được phái tới Israel để tìm hiểu Công ty công nghiệp điện tử Rada, đơn vị sản xuất hệ thống radar giám sát trên không chiến thuật RPS-42. Hệ thống này có thể phát hiện vật thể trên không trong phạm vi có bán kính 30 km và phân biệt UAV nhỏ như 3 UAV nói trên trong vòng 10 km.</p> <p>Ngoài ra, Hàn Quốc còn xúc tiến mua bổ sung thiết bị giám sát hiện có như kính viễn vọng đa năng để triển khai tới khu vực biên giới liên Triều. Giới chức Hàn Quốc cũng đang xem xét sắm một hệ thống vũ khí laser có khả năng phá hủy hiệu quả UAV đối phương xâm nhập, thông qua sự kết hợp với radar giám sát tầm thấp.</p> <p>Trong khi đó, một nhóm sĩ quan và chuyên gia Hàn Quốc đang điều tra loại động cơ, nhiên liệu và một số đặc điểm khác của 3 UAV nói trên nhằm tìm ra bằng chứng thuyết phục cho thấy chúng đến từ Triều Tiên, dù Bình Nhưỡng đã tuyên bố không có liên quan. </p> <p>Dự kiến, Bộ Quốc phòng Hàn Quốc sẽ công bố kết quả điều tra trong tuần này.</p> <p>Bộ Quốc phòng Hàn Quốc ước tính Triều Tiên có khoảng 300 UAV do thám, gần 10 UAV tấn công và đang phát triển UAV đa năng.</p> <p><strong>Văn Khoa </strong></p> </div><br /></td> </tr> <tr> <td> </td> </tr> <tr> <td> </td> </tr> <tr> <td> <p><span class='storyInlinePhoto'><img src='http://www.thanhnien.com.vn/Pictures201404/Minh_Nguyet/maybay06058541.jpg' /></span> <span>Một UAV rơi ở Hàn Quốc bị nghi là của Triều Tiên - Ảnh: Reuters</span></p> </td> </tr>",
  "key": [
    "Rađa",
    "Hàn Quốc",
    "Triều Tiên",
    "giám sát",
    "Israel",
    "ứng phó",
    "phát hiện",
    "Bộ Quốc Phòng",
    "xúc tiến",
    "xâm nhập",
    "máy bay không người lái",
    "CHDCND Triều Tiên",
    "Reuters",
    "La-de",
    "Bình Nhưỡng"
  ],
  "trends": [
    {
      "word": "Ấn Độ Dương",
      "weight": "6"
    },
    {
      "word": "Australia",
      "weight": "4"
    },
    {
      "word": "Barack Obama",
      "weight": "3"
    },
    {
      "word": "Biển Đen",
      "weight": "5"
    },
    {
      "word": "biển Đông",
      "weight": "6"
    },
    {
      "word": "Châu Âu",
      "weight": "3"
    },
    {
      "word": "Crimea",
      "weight": "1"
    },
    {
      "word": "Gazprom",
      "weight": "5"
    },
    {
      "word": "Hàn Quốc",
      "weight": "3"
    },
    {
      "word": "IMF",
      "weight": "6"
    },
    {
      "word": "Kiev",
      "weight": "1"
    },
    {
      "word": "Liên minh châu Âu",
      "weight": "2"
    },
    {
      "word": "Malaysia",
      "weight": "4"
    },
    {
      "word": "Malaysia Airlines",
      "weight": "5"
    },
    {
      "word": "máy bay chiến đấu",
      "weight": "6"
    },
    {
      "word": "Moscow",
      "weight": "3"
    },
    {
      "word": "Mỹ",
      "weight": "1"
    },
    {
      "word": "NATO",
      "weight": "2"
    },
    {
      "word": "Nga",
      "weight": "1"
    },
    {
      "word": "người biểu tình",
      "weight": "2"
    },
    {
      "word": "Nhật Bản",
      "weight": "5"
    },
    {
      "word": "Philippines",
      "weight": "4"
    },
    {
      "word": "tàu chiến",
      "weight": "4"
    },
    {
      "word": "thủ tướng Australia",
      "weight": "5"
    },
    {
      "word": "tổng thống Nga",
      "weight": "5"
    },
    {
      "word": "Triều Tiên",
      "weight": "3"
    },
    {
      "word": "Trung Quốc",
      "weight": "2"
    },
    {
      "word": "Ukraina",
      "weight": "1"
    },
    {
      "word": "Vladimir Putin",
      "weight": "2"
    },
    {
      "word": "Washington",
      "weight": "6"
    }
  ]
}
