{
  "url": "http://www.baomoi.com/Nghi-sy-My-quan-ngai-chinh-sach-doi-ngoai-cua-Nha-Trang/119/13519948.epi",
  "time": "12/04/2014 12:08",
  "title": "Nghị sỹ Mỹ quan ngại chính sách đối ngoại của Nhà Trắng",
  "category": "Tin tức > Thế giới",
  "description": "Đối mặt với hàng loạt chỉ trích mạnh mẽ từ giới nghị sỹ Mỹ, Ngoại trưởng Mỹ John Kerry ngày 8/4 tuyên bố ông sẽ chịu trách nhiệm nếu chính sách đối ngoại Washington thất bại.",
  "content": "<tr> <td> <div> <div> <div> <span class='storyInlinePhoto'><img src='http://img1.vietnamplus.vn/t660/Uploaded/lepz/2014_04_09/kerry.jpg' /></span> <span>Ngoại trưởng Mỹ John Kerry (phải) gặp Thủ tướng Benjamin Netanyahu tại Jerusalem ngày 31/3. (Nguồn: AFP/TTXVN)</span> </div> <br /> <br /> <br /> Tuy nhiên, quan chức ngoại giao này khẳng định chính quyền Tổng thống Barack Obama đang nỗ lực đạt tiến triển trong nhiều vấn đề quốc tế. <br /> <br /> Trong phiên điều trần kéo dài 2 tiếng rưỡi trước Ủy ban Đối ngoại Thượng viện Mỹ, Ngoại trưởng Kerry nhận định nguy cơ các nỗ lực ngoại giao tại các điểm nóng, đặc biệt tại Trung Đông, thất bại là không thể tránh khỏi. <br /> <br /> Tuy nhiên, ông khẳng định các vấn đề trên đều đáng để bỏ công sức và điều quan trọng là nước Mỹ cần củng cố vị trí cường quốc số một thế giới của mình. <br /> <br /> Những phát biểu của Ngoại trưởng Kerry đưa ra nhằm đáp lại những chỉ trích gay gắt của Thượng nghị sỹ Cộng hòa John McCain cho rằng chính sách đối ngoại của chính quyền Obama đang 'thất bại thảm hại' trong những vấn đề lớn. <br /> <br /> Theo ông McCain, hội nghị Geneva II về vấn đề Syria cũng như tiến trình đàm phán hòa bình Israel - Palestines đều là những sai lầm về mặt ngoại giao và đàm phán hạt nhân với Iran cũng sẽ sớm sa vết xe đổ này. <br /> <br /> Tại phiên điều trần, Ngoại trưởng Kerry đã phải đối mặt với nhiều chất vấn về chính sách đối ngoại của Nhà Trắng trong một loạt vấn đề, từ cuộc nội chiến Syria, khủng hoảng tại Bán đảo Crimea và Ukraine cũng như tiến trình đàm phán hòa bình Israel-Palestine và chương trình hạt nhân Iran. <br /> <br /> Các ý kiến chỉ trích cho rằng chính sách đối ngoại lộn xộn đang làm suy yếu nước Mỹ và khiến Washington trở nên 'yếu thế' hơn khi tham gia vào sân chơi quốc tế. <br /> <br /> Các chỉ trích trong phiên điều trần chủ yếu đến từ các Thượng nghị sỹ Cộng hòa. Trong thời gian qua, phe Cộng hòa đã liên tục nhận xét chính sách đối ngoại của chính quyền Obama là yếu kém và không hiệu quả, nhằm hạ thấp uy tín của phe Dân chủ khi cuộc bầu cử Quốc hội giữa nhiệm kỳ vào tháng 11 đang tới gần./. </div> </div><br /></td> </tr>",
  "key": [
    "đối ngoại",
    "điều trần",
    "chính sách",
    "chỉ trích",
    "Chính quyền Obama",
    "đàm phán hòa bình",
    "nghị sỹ",
    "John Kerry",
    "cộng hòa",
    "thượng nghị sỹ",
    "bộ trưởng ngoại giao",
    "Nhà Trắng",
    "Mỹ",
    "ngoại trưởng Mỹ",
    "Washington"
  ],
  "trends": [
    {
      "word": "Ấn Độ Dương",
      "weight": "6"
    },
    {
      "word": "Australia",
      "weight": "4"
    },
    {
      "word": "Barack Obama",
      "weight": "3"
    },
    {
      "word": "Biển Đen",
      "weight": "5"
    },
    {
      "word": "biển Đông",
      "weight": "6"
    },
    {
      "word": "Châu Âu",
      "weight": "3"
    },
    {
      "word": "Crimea",
      "weight": "1"
    },
    {
      "word": "Gazprom",
      "weight": "5"
    },
    {
      "word": "Hàn Quốc",
      "weight": "3"
    },
    {
      "word": "IMF",
      "weight": "6"
    },
    {
      "word": "Kiev",
      "weight": "1"
    },
    {
      "word": "Liên minh châu Âu",
      "weight": "2"
    },
    {
      "word": "Malaysia",
      "weight": "4"
    },
    {
      "word": "Malaysia Airlines",
      "weight": "5"
    },
    {
      "word": "máy bay chiến đấu",
      "weight": "6"
    },
    {
      "word": "Moscow",
      "weight": "3"
    },
    {
      "word": "Mỹ",
      "weight": "1"
    },
    {
      "word": "NATO",
      "weight": "2"
    },
    {
      "word": "Nga",
      "weight": "1"
    },
    {
      "word": "người biểu tình",
      "weight": "2"
    },
    {
      "word": "Nhật Bản",
      "weight": "5"
    },
    {
      "word": "Philippines",
      "weight": "4"
    },
    {
      "word": "tàu chiến",
      "weight": "4"
    },
    {
      "word": "thủ tướng Australia",
      "weight": "5"
    },
    {
      "word": "tổng thống Nga",
      "weight": "5"
    },
    {
      "word": "Triều Tiên",
      "weight": "3"
    },
    {
      "word": "Trung Quốc",
      "weight": "2"
    },
    {
      "word": "Ukraina",
      "weight": "1"
    },
    {
      "word": "Vladimir Putin",
      "weight": "2"
    },
    {
      "word": "Washington",
      "weight": "6"
    }
  ]
}
